{
  "operationId": "MeasurementOperations_ProvideMetadataFileDownloadInformation",
  "title": "Returns a SAS-signed URI for downloading a metadata file for the measurement.\nThis URI expires in 24 hours.",
  "parameters": {
    "measurementId": "00000000-0000-0000-0000-000000000003",
    "api-version": "2023-00-00-preview"
  },
  "responses": {
    "200": {
      "body": {
        "resourceEndpoint": "https://some-workspace/some-resource",
        "fileDownloadUri": "https://microsoft.com/a"
      }
    },
    "default": {
      "body": {
        "error": {
          "code": "string",
          "message": "string",
          "target": "string",
          "details": []
        }
      }
    }
  }
}
